{"content": {"suites": {"0": {"status": {"total_pass": 2, "total_skip": 0, "total_xpass": 0, "total_xfail": 0, "total_rerun": 0, "total_fail": 0, "total_error": 0}, "tests": {"0": {"status": "PASS", "message": "", "test_name": "test_go_to_page", "rerun": "0"}, "1": {"status": "PASS", "message": "", "test_name": "test_login", "rerun": "0"}}, "suite_name": "tests/login_tests/test_login_1.py"}, "1": {"suite_name": "tests/login_tests/test_login_2.py", "tests": {"0": {"status": "PASS", "message": "", "test_name": "test_go_to_page", "rerun": "0"}, "1": {"status": "PASS", "message": "", "test_name": "test_email_inputs[a]", "rerun": "0"}, "2": {"status": "PASS", "message": "", "test_name": "test_email_inputs[Yaro]", "rerun": "0"}, "3": {"status": "PASS", "message": "", "test_name": "test_email_inputs[Baro]", "rerun": "0"}, "4": {"status": "PASS", "message": "", "test_name": "test_email_inputs[YaroBaro.com]", "rerun": "0"}, "5": {"status": "PASS", "message": "", "test_name": "test_email_inputs[@]", "rerun": "0"}, "6": {"status": "PASS", "message": "", "test_name": "test_email_inputs[ ]", "rerun": "0"}, "7": {"status": "PASS", "message": "", "test_name": "test_login_inputs[B]", "rerun": "0"}, "8": {"status": "PASS", "message": "", "test_name": "test_login_inputs[Baro]", "rerun": "0"}, "9": {"status": "PASS", "message": "", "test_name": "test_login_inputs[BaroYaro]", "rerun": "0"}, "10": {"status": "PASS", "message": "", "test_name": "test_login_inputs[ ]", "rerun": "0"}, "11": {"status": "PASS", "message": "", "test_name": "test_login_inputs[@]", "rerun": "0"}}, "status": {"total_pass": 12, "total_skip": 0, "total_xpass": 0, "total_xfail": 0, "total_rerun": 0, "total_fail": 0, "total_error": 0}}}}, "date": "December 12, 2022", "start_time": 1670877595.011674, "total_suite": 2, "status": "PASS", "status_list": {"pass": "14", "fail": "0", "skip": "0", "error": "0", "xpass": "0", "xfail": "0", "rerun": "0"}, "total_tests": "14"}